atty/__init__.py
atty/main.py
atty/py.typed
atty/version.py
atty-0.1.0.dist-info/LICENSE
atty-0.1.0.dist-info/METADATA
atty-0.1.0.dist-info/WHEEL
atty-0.1.0.dist-info/entry_points.txt
atty-0.1.0.dist-info/top_level.txt
atty-0.1.0.dist-info/RECORD
