Metadata-Version: 2.1
Name: atty
Version: 0.1.0
Author-email: Michell Stuttgart <michellstut@gmail.com>
License: MIT License
Project-URL: Homepage, https://github.com/mstuttgart/atty
Project-URL: Repository, https://github.com/mstuttgart/atty
Project-URL: Changelog, https://github.com/mstuttgart/atty/blob/main/CHANGELOG.md
Keywords: cli,interactive,console,terminal,alacritty
Classifier: Development Status :: 4 - Beta
Classifier: License :: OSI Approved :: MIT License
Classifier: Programming Language :: Python
Classifier: Programming Language :: Python :: 3
Classifier: Programming Language :: Python :: 3 :: Only
Classifier: Programming Language :: Python :: 3.8
Classifier: Programming Language :: Python :: 3.9
Classifier: Programming Language :: Python :: 3.10
Classifier: Programming Language :: Python :: 3.11
Classifier: Programming Language :: Python :: 3.12
Classifier: Topic :: Terminals
Classifier: Environment :: Console
Classifier: Intended Audience :: Developers
Requires-Python: >=3.8
License-File: LICENSE
Requires-Dist: click
Requires-Dist: beaupy
Requires-Dist: tomli
Requires-Dist: tomli-w
Provides-Extra: coverage
Requires-Dist: coveralls >=3.3.1 ; extra == 'coverage'
Requires-Dist: pytest-cov >=4.0.0 ; extra == 'coverage'
Requires-Dist: requests-mock >=1.10.0 ; extra == 'coverage'
Provides-Extra: dev
Requires-Dist: nox >=2022.11.21 ; extra == 'dev'
Requires-Dist: ruff ; extra == 'dev'
Requires-Dist: black <24.0,>=23.0 ; extra == 'dev'
Requires-Dist: isort <5.13,>=5.12 ; extra == 'dev'
Requires-Dist: pytest ; extra == 'dev'
Provides-Extra: release
Requires-Dist: twine >=1.11.0 ; extra == 'release'
Requires-Dist: build ; extra == 'release'
Requires-Dist: setuptools ; extra == 'release'
Requires-Dist: wheel ; extra == 'release'
Requires-Dist: packaging ; extra == 'release'
